datapipe/__init__.py
datapipe/cli.py
datapipe/core.py
datapipemath-0.1.1.dist-info/licenses/LICENSE
datapipemath-0.1.1.dist-info/METADATA
datapipemath-0.1.1.dist-info/WHEEL
datapipemath-0.1.1.dist-info/entry_points.txt
datapipemath-0.1.1.dist-info/top_level.txt
datapipemath-0.1.1.dist-info/RECORD
