Metadata-Version: 2.4
Name: datapipemath
Version: 0.1.1
Summary: data pipeline tool
Author-email: Data Pipe <datapipe@gmail.com>
License: MIT
Keywords: datapipe
Classifier: Development Status :: 4 - Beta
Classifier: Intended Audience :: Developers
Classifier: License :: OSI Approved :: MIT License
Classifier: Programming Language :: Python :: 3
Classifier: Programming Language :: Python :: 3.8
Classifier: Programming Language :: Python :: 3.9
Classifier: Programming Language :: Python :: 3.10
Classifier: Programming Language :: Python :: 3.11
Classifier: Programming Language :: Python :: 3.12
Requires-Python: >=3.8
License-File: LICENSE
Requires-Dist: pyautogui>=0.9.54
Provides-Extra: dev
Requires-Dist: build>=1.0; extra == "dev"
Requires-Dist: twine>=4.0; extra == "dev"
Dynamic: license-file
